kitsune/__init__.py
kitsune/kitsune.py
kitsune/modules/__init__.py
kitsune/modules/acf.py
kitsune/modules/cre.py
kitsune/modules/dmatrix.py
kitsune/modules/kitsunejf.py
kitsune/modules/kopt.py
kitsune/modules/ofc.py
kitsune/tests/__init__.py
kitsune/tests/test_kitsunejf.py
kitsune/tests/test_main.py
kitsune-1.3.5.dist-info/LICENSE
kitsune-1.3.5.dist-info/METADATA
kitsune-1.3.5.dist-info/WHEEL
kitsune-1.3.5.dist-info/entry_points.txt
kitsune-1.3.5.dist-info/top_level.txt
kitsune-1.3.5.dist-info/RECORD
