Metadata-Version: 2.1
Name: kitsune
Version: 1.3.5
Summary: A toolkit for evaluation of the lenght of k-mer in a given genome dataset for alignment-free phylogenimic analysis
Home-page: https://github.com/natapol/kitsune
Download-URL: https://pypi.org/project/kitsune/
Author: Natapol Pornputtapong
Author-email: natapol.por@gmail.com
License: GPL-3.0 License
Keywords: bioinformatics,kitsune
Classifier: Development Status :: 5 - Production/Stable
Classifier: License :: OSI Approved :: GNU General Public License v3 (GPLv3)
Classifier: Programming Language :: Python :: 3.6
Classifier: Programming Language :: Python :: 3.7
Classifier: Topic :: Scientific/Engineering :: Bio-Informatics
Classifier: Operating System :: POSIX :: Linux
Classifier: Operating System :: MacOS :: MacOS X
Requires-Python: >=3.5
License-File: LICENSE
Requires-Dist: numpy >=1.1.0
Requires-Dist: scipy >=0.18.1
Requires-Dist: tqdm >=4.32
